
{"items":[{"name":"CXEX.Build.Emitters","href":"CXEX.Build.Emitters.html","topicHref":"CXEX.Build.Emitters.html","topicUid":"CXEX.Build.Emitters","type":"Namespace","items":[{"name":"CXEXWriter","href":"CXEX.Build.Emitters.CXEXWriter.html","topicHref":"CXEX.Build.Emitters.CXEXWriter.html","topicUid":"CXEX.Build.Emitters.CXEXWriter","type":"Class"},{"name":"StagedFile","href":"CXEX.Build.Emitters.StagedFile.html","topicHref":"CXEX.Build.Emitters.StagedFile.html","topicUid":"CXEX.Build.Emitters.StagedFile","type":"Class"},{"name":"XBPTImageWriter","href":"CXEX.Build.Emitters.XBPTImageWriter.html","topicHref":"CXEX.Build.Emitters.XBPTImageWriter.html","topicUid":"CXEX.Build.Emitters.XBPTImageWriter","type":"Class"}]},{"name":"CXEX.Build.Engines","href":"CXEX.Build.Engines.html","topicHref":"CXEX.Build.Engines.html","topicUid":"CXEX.Build.Engines","type":"Namespace","items":[{"name":"CXEXLayoutEngine","href":"CXEX.Build.Engines.CXEXLayoutEngine.html","topicHref":"CXEX.Build.Engines.CXEXLayoutEngine.html","topicUid":"CXEX.Build.Engines.CXEXLayoutEngine","type":"Class"},{"name":"DiskGeometryEngine","href":"CXEX.Build.Engines.DiskGeometryEngine.html","topicHref":"CXEX.Build.Engines.DiskGeometryEngine.html","topicUid":"CXEX.Build.Engines.DiskGeometryEngine","type":"Class"}]},{"name":"CXEX.Build.Layout","href":"CXEX.Build.Layout.html","topicHref":"CXEX.Build.Layout.html","topicUid":"CXEX.Build.Layout","type":"Namespace","items":[{"name":"CxexMemoryLayout","href":"CXEX.Build.Layout.CxexMemoryLayout.html","topicHref":"CXEX.Build.Layout.CxexMemoryLayout.html","topicUid":"CXEX.Build.Layout.CxexMemoryLayout","type":"Class"},{"name":"DiskGeometryMap","href":"CXEX.Build.Layout.DiskGeometryMap.html","topicHref":"CXEX.Build.Layout.DiskGeometryMap.html","topicUid":"CXEX.Build.Layout.DiskGeometryMap","type":"Class"},{"name":"PartitionLayout","href":"CXEX.Build.Layout.PartitionLayout.html","topicHref":"CXEX.Build.Layout.PartitionLayout.html","topicUid":"CXEX.Build.Layout.PartitionLayout","type":"Class"},{"name":"SectionLayout","href":"CXEX.Build.Layout.SectionLayout.html","topicHref":"CXEX.Build.Layout.SectionLayout.html","topicUid":"CXEX.Build.Layout.SectionLayout","type":"Class"}]},{"name":"CXEX.Build.Parsers","href":"CXEX.Build.Parsers.html","topicHref":"CXEX.Build.Parsers.html","topicUid":"CXEX.Build.Parsers","type":"Namespace","items":[{"name":"ElfParser","href":"CXEX.Build.Parsers.ElfParser.html","topicHref":"CXEX.Build.Parsers.ElfParser.html","topicUid":"CXEX.Build.Parsers.ElfParser","type":"Class"},{"name":"ElfSegment","href":"CXEX.Build.Parsers.ElfSegment.html","topicHref":"CXEX.Build.Parsers.ElfSegment.html","topicUid":"CXEX.Build.Parsers.ElfSegment","type":"Class"}]},{"name":"CXEX.CLI.Commands","href":"CXEX.CLI.Commands.html","topicHref":"CXEX.CLI.Commands.html","topicUid":"CXEX.CLI.Commands","type":"Namespace","items":[{"name":"BuildCommand","href":"CXEX.CLI.Commands.BuildCommand.html","topicHref":"CXEX.CLI.Commands.BuildCommand.html","topicUid":"CXEX.CLI.Commands.BuildCommand","type":"Class"},{"name":"BuildCommand.Settings","href":"CXEX.CLI.Commands.BuildCommand.Settings.html","topicHref":"CXEX.CLI.Commands.BuildCommand.Settings.html","topicUid":"CXEX.CLI.Commands.BuildCommand.Settings","type":"Class"},{"name":"CheckCommand","href":"CXEX.CLI.Commands.CheckCommand.html","topicHref":"CXEX.CLI.Commands.CheckCommand.html","topicUid":"CXEX.CLI.Commands.CheckCommand","type":"Class"},{"name":"CheckCommand.Settings","href":"CXEX.CLI.Commands.CheckCommand.Settings.html","topicHref":"CXEX.CLI.Commands.CheckCommand.Settings.html","topicUid":"CXEX.CLI.Commands.CheckCommand.Settings","type":"Class"},{"name":"CompileCommand","href":"CXEX.CLI.Commands.CompileCommand.html","topicHref":"CXEX.CLI.Commands.CompileCommand.html","topicUid":"CXEX.CLI.Commands.CompileCommand","type":"Class"},{"name":"CompileCommand.Settings","href":"CXEX.CLI.Commands.CompileCommand.Settings.html","topicHref":"CXEX.CLI.Commands.CompileCommand.Settings.html","topicUid":"CXEX.CLI.Commands.CompileCommand.Settings","type":"Class"},{"name":"EmbedCommand","href":"CXEX.CLI.Commands.EmbedCommand.html","topicHref":"CXEX.CLI.Commands.EmbedCommand.html","topicUid":"CXEX.CLI.Commands.EmbedCommand","type":"Class"},{"name":"EmbedCommand.Settings","href":"CXEX.CLI.Commands.EmbedCommand.Settings.html","topicHref":"CXEX.CLI.Commands.EmbedCommand.Settings.html","topicUid":"CXEX.CLI.Commands.EmbedCommand.Settings","type":"Class"},{"name":"ImageCommand","href":"CXEX.CLI.Commands.ImageCommand.html","topicHref":"CXEX.CLI.Commands.ImageCommand.html","topicUid":"CXEX.CLI.Commands.ImageCommand","type":"Class"},{"name":"ImageCommand.Settings","href":"CXEX.CLI.Commands.ImageCommand.Settings.html","topicHref":"CXEX.CLI.Commands.ImageCommand.Settings.html","topicUid":"CXEX.CLI.Commands.ImageCommand.Settings","type":"Class"},{"name":"InspectCommand","href":"CXEX.CLI.Commands.InspectCommand.html","topicHref":"CXEX.CLI.Commands.InspectCommand.html","topicUid":"CXEX.CLI.Commands.InspectCommand","type":"Class"},{"name":"InspectCommand.Settings","href":"CXEX.CLI.Commands.InspectCommand.Settings.html","topicHref":"CXEX.CLI.Commands.InspectCommand.Settings.html","topicUid":"CXEX.CLI.Commands.InspectCommand.Settings","type":"Class"},{"name":"KeygenCommand","href":"CXEX.CLI.Commands.KeygenCommand.html","topicHref":"CXEX.CLI.Commands.KeygenCommand.html","topicUid":"CXEX.CLI.Commands.KeygenCommand","type":"Class"},{"name":"KeygenCommand.Settings","href":"CXEX.CLI.Commands.KeygenCommand.Settings.html","topicHref":"CXEX.CLI.Commands.KeygenCommand.Settings.html","topicUid":"CXEX.CLI.Commands.KeygenCommand.Settings","type":"Class"},{"name":"RawImageCommand","href":"CXEX.CLI.Commands.RawImageCommand.html","topicHref":"CXEX.CLI.Commands.RawImageCommand.html","topicUid":"CXEX.CLI.Commands.RawImageCommand","type":"Class"},{"name":"RawImageCommand.Settings","href":"CXEX.CLI.Commands.RawImageCommand.Settings.html","topicHref":"CXEX.CLI.Commands.RawImageCommand.Settings.html","topicUid":"CXEX.CLI.Commands.RawImageCommand.Settings","type":"Class"},{"name":"RunCommand","href":"CXEX.CLI.Commands.RunCommand.html","topicHref":"CXEX.CLI.Commands.RunCommand.html","topicUid":"CXEX.CLI.Commands.RunCommand","type":"Class"},{"name":"RunCommand.Settings","href":"CXEX.CLI.Commands.RunCommand.Settings.html","topicHref":"CXEX.CLI.Commands.RunCommand.Settings.html","topicUid":"CXEX.CLI.Commands.RunCommand.Settings","type":"Class"},{"name":"SignCommand","href":"CXEX.CLI.Commands.SignCommand.html","topicHref":"CXEX.CLI.Commands.SignCommand.html","topicUid":"CXEX.CLI.Commands.SignCommand","type":"Class"},{"name":"SignCommand.Settings","href":"CXEX.CLI.Commands.SignCommand.Settings.html","topicHref":"CXEX.CLI.Commands.SignCommand.Settings.html","topicUid":"CXEX.CLI.Commands.SignCommand.Settings","type":"Class"}]},{"name":"CXEX.CLI.Infrastructure","href":"CXEX.CLI.Infrastructure.html","topicHref":"CXEX.CLI.Infrastructure.html","topicUid":"CXEX.CLI.Infrastructure","type":"Namespace","items":[{"name":"ProcessRunner","href":"CXEX.CLI.Infrastructure.ProcessRunner.html","topicHref":"CXEX.CLI.Infrastructure.ProcessRunner.html","topicUid":"CXEX.CLI.Infrastructure.ProcessRunner","type":"Class"}]},{"name":"CXEX.CLI.Wrappers","href":"CXEX.CLI.Wrappers.html","topicHref":"CXEX.CLI.Wrappers.html","topicUid":"CXEX.CLI.Wrappers","type":"Namespace","items":[{"name":"BochsConfig","href":"CXEX.CLI.Wrappers.BochsConfig.html","topicHref":"CXEX.CLI.Wrappers.BochsConfig.html","topicUid":"CXEX.CLI.Wrappers.BochsConfig","type":"Class"},{"name":"BochsTool","href":"CXEX.CLI.Wrappers.BochsTool.html","topicHref":"CXEX.CLI.Wrappers.BochsTool.html","topicUid":"CXEX.CLI.Wrappers.BochsTool","type":"Class"},{"name":"CMakeTool","href":"CXEX.CLI.Wrappers.CMakeTool.html","topicHref":"CXEX.CLI.Wrappers.CMakeTool.html","topicUid":"CXEX.CLI.Wrappers.CMakeTool","type":"Class"},{"name":"GccTool","href":"CXEX.CLI.Wrappers.GccTool.html","topicHref":"CXEX.CLI.Wrappers.GccTool.html","topicUid":"CXEX.CLI.Wrappers.GccTool","type":"Class"},{"name":"NasmTool","href":"CXEX.CLI.Wrappers.NasmTool.html","topicHref":"CXEX.CLI.Wrappers.NasmTool.html","topicUid":"CXEX.CLI.Wrappers.NasmTool","type":"Class"},{"name":"QemuConfig","href":"CXEX.CLI.Wrappers.QemuConfig.html","topicHref":"CXEX.CLI.Wrappers.QemuConfig.html","topicUid":"CXEX.CLI.Wrappers.QemuConfig","type":"Class"},{"name":"QemuTool","href":"CXEX.CLI.Wrappers.QemuTool.html","topicHref":"CXEX.CLI.Wrappers.QemuTool.html","topicUid":"CXEX.CLI.Wrappers.QemuTool","type":"Class"}]},{"name":"CXEX.Core.Constants","href":"CXEX.Core.Constants.html","topicHref":"CXEX.Core.Constants.html","topicUid":"CXEX.Core.Constants","type":"Namespace","items":[{"name":"CXFlags","href":"CXEX.Core.Constants.CXFlags.html","topicHref":"CXEX.Core.Constants.CXFlags.html","topicUid":"CXEX.Core.Constants.CXFlags","type":"Class"},{"name":"CXMagic","href":"CXEX.Core.Constants.CXMagic.html","topicHref":"CXEX.Core.Constants.CXMagic.html","topicUid":"CXEX.Core.Constants.CXMagic","type":"Class"}]},{"name":"CXEX.Core.Interfaces","href":"CXEX.Core.Interfaces.html","topicHref":"CXEX.Core.Interfaces.html","topicUid":"CXEX.Core.Interfaces","type":"Namespace","items":[{"name":"ICXFile","href":"CXEX.Core.Interfaces.ICXFile.html","topicHref":"CXEX.Core.Interfaces.ICXFile.html","topicUid":"CXEX.Core.Interfaces.ICXFile","type":"Interface"},{"name":"ICXFileSystem","href":"CXEX.Core.Interfaces.ICXFileSystem.html","topicHref":"CXEX.Core.Interfaces.ICXFileSystem.html","topicUid":"CXEX.Core.Interfaces.ICXFileSystem","type":"Interface"}]},{"name":"CXEX.Core.Utilities","href":"CXEX.Core.Utilities.html","topicHref":"CXEX.Core.Utilities.html","topicUid":"CXEX.Core.Utilities","type":"Namespace","items":[{"name":"MemoryPrimitives","href":"CXEX.Core.Utilities.MemoryPrimitives.html","topicHref":"CXEX.Core.Utilities.MemoryPrimitives.html","topicUid":"CXEX.Core.Utilities.MemoryPrimitives","type":"Class"}]},{"name":"CXEX.Crypto.Signing","href":"CXEX.Crypto.Signing.html","topicHref":"CXEX.Crypto.Signing.html","topicUid":"CXEX.Crypto.Signing","type":"Namespace","items":[{"name":"CXSigner","href":"CXEX.Crypto.Signing.CXSigner.html","topicHref":"CXEX.Crypto.Signing.CXSigner.html","topicUid":"CXEX.Crypto.Signing.CXSigner","type":"Class"},{"name":"CXVerifier","href":"CXEX.Crypto.Signing.CXVerifier.html","topicHref":"CXEX.Crypto.Signing.CXVerifier.html","topicUid":"CXEX.Crypto.Signing.CXVerifier","type":"Class"},{"name":"CXVerifier.VerifyResult","href":"CXEX.Crypto.Signing.CXVerifier.VerifyResult.html","topicHref":"CXEX.Crypto.Signing.CXVerifier.VerifyResult.html","topicUid":"CXEX.Crypto.Signing.CXVerifier.VerifyResult","type":"Enum"}]},{"name":"CXEX.Crypto.Trust","href":"CXEX.Crypto.Trust.html","topicHref":"CXEX.Crypto.Trust.html","topicUid":"CXEX.Crypto.Trust","type":"Namespace","items":[{"name":"CXAuthChain","href":"CXEX.Crypto.Trust.CXAuthChain.html","topicHref":"CXEX.Crypto.Trust.CXAuthChain.html","topicUid":"CXEX.Crypto.Trust.CXAuthChain","type":"Class"},{"name":"CXKeyStore","href":"CXEX.Crypto.Trust.CXKeyStore.html","topicHref":"CXEX.Crypto.Trust.CXKeyStore.html","topicUid":"CXEX.Crypto.Trust.CXKeyStore","type":"Class"}]},{"name":"CXEX.Disk","href":"CXEX.Disk.html","topicHref":"CXEX.Disk.html","topicUid":"CXEX.Disk","type":"Namespace","items":[{"name":"DiskAnalyzer","href":"CXEX.Disk.DiskAnalyzer.html","topicHref":"CXEX.Disk.DiskAnalyzer.html","topicUid":"CXEX.Disk.DiskAnalyzer","type":"Class"}]},{"name":"CXEX.Disk.Models","href":"CXEX.Disk.Models.html","topicHref":"CXEX.Disk.Models.html","topicUid":"CXEX.Disk.Models","type":"Namespace","items":[{"name":"DiskLayout","href":"CXEX.Disk.Models.DiskLayout.html","topicHref":"CXEX.Disk.Models.DiskLayout.html","topicUid":"CXEX.Disk.Models.DiskLayout","type":"Class"},{"name":"PartitionEntry","href":"CXEX.Disk.Models.PartitionEntry.html","topicHref":"CXEX.Disk.Models.PartitionEntry.html","topicUid":"CXEX.Disk.Models.PartitionEntry","type":"Class"},{"name":"PartitionTableType","href":"CXEX.Disk.Models.PartitionTableType.html","topicHref":"CXEX.Disk.Models.PartitionTableType.html","topicUid":"CXEX.Disk.Models.PartitionTableType","type":"Enum"}]},{"name":"CXEX.Disk.Parsers","href":"CXEX.Disk.Parsers.html","topicHref":"CXEX.Disk.Parsers.html","topicUid":"CXEX.Disk.Parsers","type":"Namespace","items":[{"name":"GptParser","href":"CXEX.Disk.Parsers.GptParser.html","topicHref":"CXEX.Disk.Parsers.GptParser.html","topicUid":"CXEX.Disk.Parsers.GptParser","type":"Class"},{"name":"MbrParser","href":"CXEX.Disk.Parsers.MbrParser.html","topicHref":"CXEX.Disk.Parsers.MbrParser.html","topicUid":"CXEX.Disk.Parsers.MbrParser","type":"Class"},{"name":"XbptParser","href":"CXEX.Disk.Parsers.XbptParser.html","topicHref":"CXEX.Disk.Parsers.XbptParser.html","topicUid":"CXEX.Disk.Parsers.XbptParser","type":"Class"}]},{"name":"CXEX.FileSystem.Mounts","href":"CXEX.FileSystem.Mounts.html","topicHref":"CXEX.FileSystem.Mounts.html","topicUid":"CXEX.FileSystem.Mounts","type":"Namespace","items":[{"name":"CXFSFileSystem","href":"CXEX.FileSystem.Mounts.CXFSFileSystem.html","topicHref":"CXEX.FileSystem.Mounts.CXFSFileSystem.html","topicUid":"CXEX.FileSystem.Mounts.CXFSFileSystem","type":"Class"},{"name":"CXFSImage","href":"CXEX.FileSystem.Mounts.CXFSImage.html","topicHref":"CXEX.FileSystem.Mounts.CXFSImage.html","topicUid":"CXEX.FileSystem.Mounts.CXFSImage","type":"Class"},{"name":"CXMemoryFileSystem","href":"CXEX.FileSystem.Mounts.CXMemoryFileSystem.html","topicHref":"CXEX.FileSystem.Mounts.CXMemoryFileSystem.html","topicUid":"CXEX.FileSystem.Mounts.CXMemoryFileSystem","type":"Class"}]},{"name":"CXEX.FileSystem.Paths","href":"CXEX.FileSystem.Paths.html","topicHref":"CXEX.FileSystem.Paths.html","topicUid":"CXEX.FileSystem.Paths","type":"Namespace","items":[{"name":"CXPath","href":"CXEX.FileSystem.Paths.CXPath.html","topicHref":"CXEX.FileSystem.Paths.CXPath.html","topicUid":"CXEX.FileSystem.Paths.CXPath","type":"Class"}]},{"name":"CXEX.FileSystem.Volume","href":"CXEX.FileSystem.Volume.html","topicHref":"CXEX.FileSystem.Volume.html","topicUid":"CXEX.FileSystem.Volume","type":"Namespace","items":[{"name":"CXFSConstants","href":"CXEX.FileSystem.Volume.CXFSConstants.html","topicHref":"CXEX.FileSystem.Volume.CXFSConstants.html","topicUid":"CXEX.FileSystem.Volume.CXFSConstants","type":"Class"},{"name":"CXFSEntry","href":"CXEX.FileSystem.Volume.CXFSEntry.html","topicHref":"CXEX.FileSystem.Volume.CXFSEntry.html","topicUid":"CXEX.FileSystem.Volume.CXFSEntry","type":"Class"},{"name":"CXFSParser","href":"CXEX.FileSystem.Volume.CXFSParser.html","topicHref":"CXEX.FileSystem.Volume.CXFSParser.html","topicUid":"CXEX.FileSystem.Volume.CXFSParser","type":"Class"},{"name":"CXFSSuperblock","href":"CXEX.FileSystem.Volume.CXFSSuperblock.html","topicHref":"CXEX.FileSystem.Volume.CXFSSuperblock.html","topicUid":"CXEX.FileSystem.Volume.CXFSSuperblock","type":"Class"}]},{"name":"CXEX.FileType.Parsers","href":"CXEX.FileType.Parsers.html","topicHref":"CXEX.FileType.Parsers.html","topicUid":"CXEX.FileType.Parsers","type":"Namespace","items":[{"name":"CXEXParser","href":"CXEX.FileType.Parsers.CXEXParser.html","topicHref":"CXEX.FileType.Parsers.CXEXParser.html","topicUid":"CXEX.FileType.Parsers.CXEXParser","type":"Class"},{"name":"CXOtherParsers","href":"CXEX.FileType.Parsers.CXOtherParsers.html","topicHref":"CXEX.FileType.Parsers.CXOtherParsers.html","topicUid":"CXEX.FileType.Parsers.CXOtherParsers","type":"Class"}]},{"name":"CXEX.FileType.Structures","href":"CXEX.FileType.Structures.html","topicHref":"CXEX.FileType.Structures.html","topicUid":"CXEX.FileType.Structures","type":"Namespace","items":[{"name":"CXEXHeader","href":"CXEX.FileType.Structures.CXEXHeader.html","topicHref":"CXEX.FileType.Structures.CXEXHeader.html","topicUid":"CXEX.FileType.Structures.CXEXHeader","type":"Class"},{"name":"CXEXSection","href":"CXEX.FileType.Structures.CXEXSection.html","topicHref":"CXEX.FileType.Structures.CXEXSection.html","topicUid":"CXEX.FileType.Structures.CXEXSection","type":"Class"},{"name":"CXEXSignatureBlock","href":"CXEX.FileType.Structures.CXEXSignatureBlock.html","topicHref":"CXEX.FileType.Structures.CXEXSignatureBlock.html","topicUid":"CXEX.FileType.Structures.CXEXSignatureBlock","type":"Class"},{"name":"CXPKHeader","href":"CXEX.FileType.Structures.CXPKHeader.html","topicHref":"CXEX.FileType.Structures.CXPKHeader.html","topicUid":"CXEX.FileType.Structures.CXPKHeader","type":"Class"},{"name":"XBPTEntry","href":"CXEX.FileType.Structures.XBPTEntry.html","topicHref":"CXEX.FileType.Structures.XBPTEntry.html","topicUid":"CXEX.FileType.Structures.XBPTEntry","type":"Class"},{"name":"XBPTHeader","href":"CXEX.FileType.Structures.XBPTHeader.html","topicHref":"CXEX.FileType.Structures.XBPTHeader.html","topicUid":"CXEX.FileType.Structures.XBPTHeader","type":"Class"}]},{"name":"CXEX.FileType.Types","href":"CXEX.FileType.Types.html","topicHref":"CXEX.FileType.Types.html","topicUid":"CXEX.FileType.Types","type":"Namespace","items":[{"name":"CXEXExecutable","href":"CXEX.FileType.Types.CXEXExecutable.html","topicHref":"CXEX.FileType.Types.CXEXExecutable.html","topicUid":"CXEX.FileType.Types.CXEXExecutable","type":"Class"},{"name":"XBPTFile","href":"CXEX.FileType.Types.XBPTFile.html","topicHref":"CXEX.FileType.Types.XBPTFile.html","topicUid":"CXEX.FileType.Types.XBPTFile","type":"Class"},{"name":"XKPKFile","href":"CXEX.FileType.Types.XKPKFile.html","topicHref":"CXEX.FileType.Types.XKPKFile.html","topicUid":"CXEX.FileType.Types.XKPKFile","type":"Class"},{"name":"XKSKFile","href":"CXEX.FileType.Types.XKSKFile.html","topicHref":"CXEX.FileType.Types.XKSKFile.html","topicUid":"CXEX.FileType.Types.XKSKFile","type":"Class"}]},{"name":"CXEX.Lang.Abi","href":"CXEX.Lang.Abi.html","topicHref":"CXEX.Lang.Abi.html","topicUid":"CXEX.Lang.Abi","type":"Namespace","items":[{"name":"AbiPrelude","href":"CXEX.Lang.Abi.AbiPrelude.html","topicHref":"CXEX.Lang.Abi.AbiPrelude.html","topicUid":"CXEX.Lang.Abi.AbiPrelude","type":"Class"}]},{"name":"CXEX.Lang.Ast","href":"CXEX.Lang.Ast.html","topicHref":"CXEX.Lang.Ast.html","topicUid":"CXEX.Lang.Ast","type":"Namespace","items":[{"name":"ArrayType","href":"CXEX.Lang.Ast.ArrayType.html","topicHref":"CXEX.Lang.Ast.ArrayType.html","topicUid":"CXEX.Lang.Ast.ArrayType","type":"Class"},{"name":"AssignStmt","href":"CXEX.Lang.Ast.AssignStmt.html","topicHref":"CXEX.Lang.Ast.AssignStmt.html","topicUid":"CXEX.Lang.Ast.AssignStmt","type":"Class"},{"name":"BinOp","href":"CXEX.Lang.Ast.BinOp.html","topicHref":"CXEX.Lang.Ast.BinOp.html","topicUid":"CXEX.Lang.Ast.BinOp","type":"Enum"},{"name":"BinaryExpr","href":"CXEX.Lang.Ast.BinaryExpr.html","topicHref":"CXEX.Lang.Ast.BinaryExpr.html","topicUid":"CXEX.Lang.Ast.BinaryExpr","type":"Class"},{"name":"Block","href":"CXEX.Lang.Ast.Block.html","topicHref":"CXEX.Lang.Ast.Block.html","topicUid":"CXEX.Lang.Ast.Block","type":"Class"},{"name":"BoolLit","href":"CXEX.Lang.Ast.BoolLit.html","topicHref":"CXEX.Lang.Ast.BoolLit.html","topicUid":"CXEX.Lang.Ast.BoolLit","type":"Class"},{"name":"CallExpr","href":"CXEX.Lang.Ast.CallExpr.html","topicHref":"CXEX.Lang.Ast.CallExpr.html","topicUid":"CXEX.Lang.Ast.CallExpr","type":"Class"},{"name":"CastExpr","href":"CXEX.Lang.Ast.CastExpr.html","topicHref":"CXEX.Lang.Ast.CastExpr.html","topicUid":"CXEX.Lang.Ast.CastExpr","type":"Class"},{"name":"CompilationUnit","href":"CXEX.Lang.Ast.CompilationUnit.html","topicHref":"CXEX.Lang.Ast.CompilationUnit.html","topicUid":"CXEX.Lang.Ast.CompilationUnit","type":"Class"},{"name":"ConstDecl","href":"CXEX.Lang.Ast.ConstDecl.html","topicHref":"CXEX.Lang.Ast.ConstDecl.html","topicUid":"CXEX.Lang.Ast.ConstDecl","type":"Class"},{"name":"Decl","href":"CXEX.Lang.Ast.Decl.html","topicHref":"CXEX.Lang.Ast.Decl.html","topicUid":"CXEX.Lang.Ast.Decl","type":"Class"},{"name":"Expr","href":"CXEX.Lang.Ast.Expr.html","topicHref":"CXEX.Lang.Ast.Expr.html","topicUid":"CXEX.Lang.Ast.Expr","type":"Class"},{"name":"ExprStmt","href":"CXEX.Lang.Ast.ExprStmt.html","topicHref":"CXEX.Lang.Ast.ExprStmt.html","topicUid":"CXEX.Lang.Ast.ExprStmt","type":"Class"},{"name":"FnDecl","href":"CXEX.Lang.Ast.FnDecl.html","topicHref":"CXEX.Lang.Ast.FnDecl.html","topicUid":"CXEX.Lang.Ast.FnDecl","type":"Class"},{"name":"GlobalDecl","href":"CXEX.Lang.Ast.GlobalDecl.html","topicHref":"CXEX.Lang.Ast.GlobalDecl.html","topicUid":"CXEX.Lang.Ast.GlobalDecl","type":"Class"},{"name":"IfStmt","href":"CXEX.Lang.Ast.IfStmt.html","topicHref":"CXEX.Lang.Ast.IfStmt.html","topicUid":"CXEX.Lang.Ast.IfStmt","type":"Class"},{"name":"IndexExpr","href":"CXEX.Lang.Ast.IndexExpr.html","topicHref":"CXEX.Lang.Ast.IndexExpr.html","topicUid":"CXEX.Lang.Ast.IndexExpr","type":"Class"},{"name":"IntLit","href":"CXEX.Lang.Ast.IntLit.html","topicHref":"CXEX.Lang.Ast.IntLit.html","topicUid":"CXEX.Lang.Ast.IntLit","type":"Class"},{"name":"LetStmt","href":"CXEX.Lang.Ast.LetStmt.html","topicHref":"CXEX.Lang.Ast.LetStmt.html","topicUid":"CXEX.Lang.Ast.LetStmt","type":"Class"},{"name":"MemberExpr","href":"CXEX.Lang.Ast.MemberExpr.html","topicHref":"CXEX.Lang.Ast.MemberExpr.html","topicUid":"CXEX.Lang.Ast.MemberExpr","type":"Class"},{"name":"NameExpr","href":"CXEX.Lang.Ast.NameExpr.html","topicHref":"CXEX.Lang.Ast.NameExpr.html","topicUid":"CXEX.Lang.Ast.NameExpr","type":"Class"},{"name":"NamedType","href":"CXEX.Lang.Ast.NamedType.html","topicHref":"CXEX.Lang.Ast.NamedType.html","topicUid":"CXEX.Lang.Ast.NamedType","type":"Class"},{"name":"Node","href":"CXEX.Lang.Ast.Node.html","topicHref":"CXEX.Lang.Ast.Node.html","topicUid":"CXEX.Lang.Ast.Node","type":"Class"},{"name":"Param","href":"CXEX.Lang.Ast.Param.html","topicHref":"CXEX.Lang.Ast.Param.html","topicUid":"CXEX.Lang.Ast.Param","type":"Class"},{"name":"PointerType","href":"CXEX.Lang.Ast.PointerType.html","topicHref":"CXEX.Lang.Ast.PointerType.html","topicUid":"CXEX.Lang.Ast.PointerType","type":"Class"},{"name":"PrimKind","href":"CXEX.Lang.Ast.PrimKind.html","topicHref":"CXEX.Lang.Ast.PrimKind.html","topicUid":"CXEX.Lang.Ast.PrimKind","type":"Enum"},{"name":"PrimType","href":"CXEX.Lang.Ast.PrimType.html","topicHref":"CXEX.Lang.Ast.PrimType.html","topicUid":"CXEX.Lang.Ast.PrimType","type":"Class"},{"name":"ReturnStmt","href":"CXEX.Lang.Ast.ReturnStmt.html","topicHref":"CXEX.Lang.Ast.ReturnStmt.html","topicUid":"CXEX.Lang.Ast.ReturnStmt","type":"Class"},{"name":"Stmt","href":"CXEX.Lang.Ast.Stmt.html","topicHref":"CXEX.Lang.Ast.Stmt.html","topicUid":"CXEX.Lang.Ast.Stmt","type":"Class"},{"name":"StructDecl","href":"CXEX.Lang.Ast.StructDecl.html","topicHref":"CXEX.Lang.Ast.StructDecl.html","topicUid":"CXEX.Lang.Ast.StructDecl","type":"Class"},{"name":"TypeRef","href":"CXEX.Lang.Ast.TypeRef.html","topicHref":"CXEX.Lang.Ast.TypeRef.html","topicUid":"CXEX.Lang.Ast.TypeRef","type":"Class"},{"name":"UnOp","href":"CXEX.Lang.Ast.UnOp.html","topicHref":"CXEX.Lang.Ast.UnOp.html","topicUid":"CXEX.Lang.Ast.UnOp","type":"Enum"},{"name":"UnaryExpr","href":"CXEX.Lang.Ast.UnaryExpr.html","topicHref":"CXEX.Lang.Ast.UnaryExpr.html","topicUid":"CXEX.Lang.Ast.UnaryExpr","type":"Class"},{"name":"WhileStmt","href":"CXEX.Lang.Ast.WhileStmt.html","topicHref":"CXEX.Lang.Ast.WhileStmt.html","topicUid":"CXEX.Lang.Ast.WhileStmt","type":"Class"}]},{"name":"CXEX.Lang.CodeGen","href":"CXEX.Lang.CodeGen.html","topicHref":"CXEX.Lang.CodeGen.html","topicUid":"CXEX.Lang.CodeGen","type":"Namespace","items":[{"name":"X86Emitter","href":"CXEX.Lang.CodeGen.X86Emitter.html","topicHref":"CXEX.Lang.CodeGen.X86Emitter.html","topicUid":"CXEX.Lang.CodeGen.X86Emitter","type":"Class"}]},{"name":"CXEX.Lang.Diagnostics","href":"CXEX.Lang.Diagnostics.html","topicHref":"CXEX.Lang.Diagnostics.html","topicUid":"CXEX.Lang.Diagnostics","type":"Namespace","items":[{"name":"Diagnostic","href":"CXEX.Lang.Diagnostics.Diagnostic.html","topicHref":"CXEX.Lang.Diagnostics.Diagnostic.html","topicUid":"CXEX.Lang.Diagnostics.Diagnostic","type":"Class"},{"name":"DiagnosticBag","href":"CXEX.Lang.Diagnostics.DiagnosticBag.html","topicHref":"CXEX.Lang.Diagnostics.DiagnosticBag.html","topicUid":"CXEX.Lang.Diagnostics.DiagnosticBag","type":"Class"},{"name":"Severity","href":"CXEX.Lang.Diagnostics.Severity.html","topicHref":"CXEX.Lang.Diagnostics.Severity.html","topicUid":"CXEX.Lang.Diagnostics.Severity","type":"Enum"},{"name":"SourceSpan","href":"CXEX.Lang.Diagnostics.SourceSpan.html","topicHref":"CXEX.Lang.Diagnostics.SourceSpan.html","topicUid":"CXEX.Lang.Diagnostics.SourceSpan","type":"Struct"}]},{"name":"CXEX.Lang.Lexer","href":"CXEX.Lang.Lexer.html","topicHref":"CXEX.Lang.Lexer.html","topicUid":"CXEX.Lang.Lexer","type":"Namespace","items":[{"name":"Lexer","href":"CXEX.Lang.Lexer.Lexer.html","topicHref":"CXEX.Lang.Lexer.Lexer.html","topicUid":"CXEX.Lang.Lexer.Lexer","type":"Class"},{"name":"Token","href":"CXEX.Lang.Lexer.Token.html","topicHref":"CXEX.Lang.Lexer.Token.html","topicUid":"CXEX.Lang.Lexer.Token","type":"Struct"},{"name":"TokenKind","href":"CXEX.Lang.Lexer.TokenKind.html","topicHref":"CXEX.Lang.Lexer.TokenKind.html","topicUid":"CXEX.Lang.Lexer.TokenKind","type":"Enum"}]},{"name":"CXEX.Lang.Parsing","href":"CXEX.Lang.Parsing.html","topicHref":"CXEX.Lang.Parsing.html","topicUid":"CXEX.Lang.Parsing","type":"Namespace","items":[{"name":"Parser","href":"CXEX.Lang.Parsing.Parser.html","topicHref":"CXEX.Lang.Parsing.Parser.html","topicUid":"CXEX.Lang.Parsing.Parser","type":"Class"}]},{"name":"CXEX.Lang.Sema","href":"CXEX.Lang.Sema.html","topicHref":"CXEX.Lang.Sema.html","topicUid":"CXEX.Lang.Sema","type":"Namespace","items":[{"name":"ConstFold","href":"CXEX.Lang.Sema.ConstFold.html","topicHref":"CXEX.Lang.Sema.ConstFold.html","topicUid":"CXEX.Lang.Sema.ConstFold","type":"Class"},{"name":"Resolver","href":"CXEX.Lang.Sema.Resolver.html","topicHref":"CXEX.Lang.Sema.Resolver.html","topicUid":"CXEX.Lang.Sema.Resolver","type":"Class"},{"name":"Scope","href":"CXEX.Lang.Sema.Scope.html","topicHref":"CXEX.Lang.Sema.Scope.html","topicUid":"CXEX.Lang.Sema.Scope","type":"Class"},{"name":"SemaContext","href":"CXEX.Lang.Sema.SemaContext.html","topicHref":"CXEX.Lang.Sema.SemaContext.html","topicUid":"CXEX.Lang.Sema.SemaContext","type":"Class"},{"name":"SymKind","href":"CXEX.Lang.Sema.SymKind.html","topicHref":"CXEX.Lang.Sema.SymKind.html","topicUid":"CXEX.Lang.Sema.SymKind","type":"Enum"},{"name":"Symbol","href":"CXEX.Lang.Sema.Symbol.html","topicHref":"CXEX.Lang.Sema.Symbol.html","topicUid":"CXEX.Lang.Sema.Symbol","type":"Class"},{"name":"TypeChecker","href":"CXEX.Lang.Sema.TypeChecker.html","topicHref":"CXEX.Lang.Sema.TypeChecker.html","topicUid":"CXEX.Lang.Sema.TypeChecker","type":"Class"}]}],"memberLayout":"SamePage"}
